Day 14/day_14.sv
`timescale 1ns / 1ps

/*
About Arbiter:
An Arbiter provides or grants access to the Resource when there are multiple requests. It can be of 2 types:
1. Priority Arbiter
2. Round Robin Arbiter
Priority Arbiter grants access of the resource to the request having the highest priority.
*/
module day_14 #(parameter no_of_ports = 4)(
               input       wire[no_of_ports-1:0] req_i,
               output      wire[no_of_ports-1:0] gnt_o   // One-hot grant signal
               );
               
assign gnt_o[0] = req_i[0]; // req_i[0] has the highest priority

genvar i;
for(i = 1; i < no_of_ports; i = i+1) begin
    assign gnt_o[i] = req_i[i] & ~(|req_i[i-1:0]);
end 
endmodule

Day 15/day_15.sv
`timescale 1ns / 1ps

// Priority arbiter without starvation
// Arbiter grants access to the device with the highest priority for a clock cycle. 
// But, if the same device was granted access in the previous clock cycle, 
// the device with the next priority is given access in the present clock cycle
// Day 14 module is also used here to find out the grant signal based on the priority

 
module day15 (
  input     wire        clk,
  input     wire        reset,

  input     wire[3:0]   req_i,
  output    logic[3:0]  gnt_o
);

  // Use mask to identify the last grant
  logic [3:0] mask_q;
  logic [3:0] nxt_mask;

  always_ff @(posedge clk or posedge reset)
    if (reset)
      mask_q <= 4'hF;
    else
      mask_q <= nxt_mask;

  // Next mask based on the current grant
  // Mask is used so that the same device is not granted access in the next clock cycle also
  always_comb begin
    nxt_mask = mask_q;
         if (gnt_o[0]) nxt_mask = 4'b1110;
    else if (gnt_o[1]) nxt_mask = 4'b1100;
    else if (gnt_o[2]) nxt_mask = 4'b1000;
    else if (gnt_o[3]) nxt_mask = 4'b0000;
  end

  // Generate the masked requests
  logic [3:0] mask_req;

  assign mask_req = req_i & mask_q;

  logic [3:0] mask_gnt;
  logic [3:0] raw_gnt;
  // Generate grants for req and masked req
  // Need to generate maskedGnt to avoid starvation
  // Need to generate rawGnt in case the same device alone requested for access in both cycles
  day_14 #(4) maskedGnt (.req_i (mask_req), .gnt_o (mask_gnt));
  day_14 #(4) rawGnt    (.req_i (req_i),    .gnt_o (raw_gnt));

  // Final grant based on mask req
  
  assign gnt_o = |mask_req ? mask_gnt : raw_gnt;

endmodule

Day 15/day_15_tb.sv
`timescale 1ns / 1ps

//Design and verify a 4-bit round robin arbiter.

/*
About Arbiter:
An Arbiter provides or grants access to the Resource when there are multiple requests. It can be of 2 types:
1. Priority Arbiter
2. Round Robin Arbiter
Priority Arbiter grants access of the resource to the request having the highest priority.
Round Robin Arbiter grants access of the resource to all the requests in a cyclic fashion unless priority arbiter. 
*/


// TB for round robin

module day15_tb ();

  logic         clk;
  logic         reset;

  logic [3:0]   req_i;
  logic [3:0]   gnt_o;

  // Instatiate the module
  day15 DAY15 (.*);

  // Clock
  always begin
    clk = 1'b1;
    #5;
    clk = 1'b0;
    #5;
  end

  // Stimulus
  initial begin
    reset <= 1'b1;
    req_i <= 4'h0;
    @(posedge clk);
    reset <= 1'b0;
    @(posedge clk);
    @(posedge clk);
    for (int i =0; i<32; i++) begin
      req_i <= $urandom_range(0, 4'hF);
      @(posedge clk);
    end
    $finish();
  end

  // VCD dump
  initial begin
    $dumpfile("day15.vcd");
    $dumpvars(0, day15_tb);
  end

endmodule

Day 15/Day 15.sim/sim_1/behav/xsim/day15.vcd
$date
   Mon Oct 31 07:41:49 2022
$end
$version
  2017.4
$end
$timescale
  1ps
$end
$scope module day15_tb $end
$var reg 1 ! clk $end
$var reg 1 " reset $end
$var reg 4 # req_i [3:0] $end
$var reg 4 $ gnt_o [3:0] $end
$scope module DAY15 $end
$var wire 1 % clk $end
$var wire 1 & reset $end
$var wire 4 ' req_i [3:0] $end
$var reg 4 $ gnt_o [3:0] $end
$var reg 4 ( mask_q [3:0] $end
$var reg 4 ) nxt_mask [3:0] $end
$var reg 4 * mask_req [3:0] $end
$var reg 4 + mask_gnt [3:0] $end
$var reg 4 , raw_gnt [3:0] $end
$scope module maskedGnt $end
$var wire 4 - req_i [3:0] $end
$var wire 4 . gnt_o [3:0] $end
$var parameter 32 / no_of_ports [31:0] $end
$upscope $end
$scope module rawGnt $end
$var wire 4 ' req_i [3:0] $end
$var wire 4 0 gnt_o [3:0] $end
$var parameter 32 1 no_of_ports [31:0] $end
$upscope $end
$upscope $end
$scope begin Block44_4 $end
$var reg 32 2 i $end
$upscope $end
$upscope $end
$enddefinitions $end
#0
$dumpvars
1!
1"
b0 #
b0 $
1%
1&
b0 '
b1111 (
b1111 )
b0 *
b0 +
b0 ,
b0 -
b0 .
b100 /
b0 0
b100 1
b0 2
$end
#5000
0!
0%
#10000
1!
0"
1%
0&
b1111 (
#15000
0!
0%
#20000
1!
1%
b1111 (
#25000
0!
0%
#30000
1!
b1001 #
b1 $
1%
b1001 '
b1111 (
b1110 )
b1001 *
b1 +
b1 ,
b1001 -
b1 .
b1 0
#35000
0!
0%
#40000
1!
b100 #
b100 $
1%
b100 '
b1110 (
b1000 )
b100 *
b100 +
b100 ,
b100 -
b100 .
b100 0
b1 2
#45000
0!
0%
#50000
1!
b0 #
b0 $
1%
b0 '
b1000 (
b0 *
b0 +
b0 ,
b0 -
b0 .
b0 0
b10 2
#55000
0!
0%
#60000
1!
b11 #
b1 $
1%
b11 '
b1000 (
b1110 )
b0 *
b1 ,
b1 0
b11 2
#65000
0!
0%
#70000
1!
b1000 #
b1000 $
1%
b1000 '
b1110 (
b0 )
b1000 *
b1000 +
b1000 ,
b1000 -
b1000 .
b1000 0
b100 2
#75000
0!
0%
#80000
1!
b1100 #
b100 $
1%
b1100 '
b0 (
b1000 )
b0 *
b0 +
b100 ,
b0 -
b0 .
b100 0
b101 2
#85000
0!
0%
#90000
1!
b11 #
b1 $
1%
b11 '
b1000 (
b1110 )
b0 *
b1 ,
b1 0
b110 2
#95000
0!
0%
#100000
1!
b0 #
b0 $
1%
b0 '
b1110 (
b0 *
b0 ,
b0 0
b111 2
#105000
0!
0%
#110000
1!
b1000 #
b1000 $
1%
b1000 '
b1110 (
b0 )
b1000 *
b1000 +
b1000 ,
b1000 -
b1000 .
b1000 0
b1000 2
#115000
0!
0%
#120000
1!
b1000 #
b1000 $
1%
b0 (
b0 *
b0 +
b0 -
b0 .
b1001 2
#125000
0!
0%
#130000
1!
b1011 #
b1 $
1%
b1011 '
b0 (
b1110 )
b0 *
b1 ,
b1 0
b1010 2
#135000
0!
0%
#140000
1!
b1001 #
b1000 $
1%
b1001 '
b1110 (
b0 )
b1000 *
b1000 +
b1000 -
b1000 .
b1 0
b1011 2
#145000
0!
0%
#150000
1!
b1111 #
b1 $
1%
b1111 '
b0 (
b1110 )
b0 *
b0 +
b0 -
b0 .
b1 0
b1100 2
#155000
0!
0%
#160000
1!
b1100 #
b100 $
1%
b1100 '
b1110 (
b1000 )
b1100 *
b100 +
b100 ,
b1100 -
b100 .
b100 0
b1101 2
#165000
0!
0%
#170000
1!
b1111 #
b1000 $
1%
b1111 '
b1000 (
b0 )
b1000 *
b1000 +
b1 ,
b1000 -
b1000 .
b1 0
b1110 2
#175000
0!
0%
#180000
1!
b110 #
b10 $
1%
b110 '
b0 (
b1100 )
b0 *
b0 +
b10 ,
b0 -
b0 .
b10 0
b1111 2
#185000
0!
0%
#190000
1!
b110 #
b100 $
1%
b1100 (
b1000 )
b100 *
b100 +
b100 -
b100 .
b10000 2
#195000
0!
0%
#200000
1!
b101 #
b1 $
1%
b101 '
b1000 (
b1110 )
b0 *
b0 +
b1 ,
b0 -
b0 .
b1 0
b10001 2
#205000
0!
0%
#210000
1!
b1111 #
b10 $
1%
b1111 '
b1110 (
b1100 )
b1110 *
b10 +
b1110 -
b10 .
b1 0
b10010 2
#215000
0!
0%
#220000
1!
b11 #
b1 $
1%
b11 '
b1100 (
b1110 )
b0 *
b0 +
b0 -
b0 .
b1 0
b10011 2
#225000
0!
0%
#230000
1!
b0 #
b0 $
1%
b0 '
b1110 (
b0 *
b0 ,
b0 0
b10100 2
#235000
0!
0%
#240000
1!
b1100 #
b100 $
1%
b1100 '
b1110 (
b1000 )
b1100 *
b100 +
b100 ,
b1100 -
b100 .
b100 0
b10101 2
#245000
0!
0%
#250000
1!
b1111 #
b1000 $
1%
b1111 '
b1000 (
b0 )
b1000 *
b1000 +
b1 ,
b1000 -
b1000 .
b1 0
b10110 2
#255000
0!
0%
#260000
1!
b110 #
b10 $
1%
b110 '
b0 (
b1100 )
b0 *
b0 +
b10 ,
b0 -
b0 .
b10 0
b10111 2
#265000
0!
0%
#270000
1!
b111 #
b100 $
1%
b111 '
b1100 (
b1000 )
b100 *
b100 +
b1 ,
b100 -
b100 .
b1 0
b11000 2
#275000
0!
0%
#280000
1!
b110 #
b10 $
1%
b110 '
b1000 (
b1100 )
b0 *
b0 +
b10 ,
b0 -
b0 .
b10 0
b11001 2
#285000
0!
0%
#290000
1!
b1010 #
b1000 $
1%
b1010 '
b1100 (
b0 )
b1000 *
b1000 +
b1000 -
b1000 .
b10 0
b11010 2
#295000
0!
0%
#300000
1!
b101 #
b1 $
1%
b101 '
b0 (
b1110 )
b0 *
b0 +
b1 ,
b0 -
b0 .
b1 0
b11011 2
#305000
0!
0%
#310000
1!
b1 #
1%
b1 '
b1110 (
b0 *
b1 0
b11100 2
#315000
0!
0%
#320000
1!
b11 #
b10 $
1%
b11 '
b1110 (
b1100 )
b10 *
b10 +
b10 -
b10 .
b1 0
b11101 2
#325000
0!
0%
#330000
1!
b11 #
b1 $
1%
b1100 (
b1110 )
b0 *
b0 +
b0 -
b0 .
b11110 2
#335000
0!
0%
#340000
1!
b1000 #
b1000 $
1%
b1000 '
b1110 (
b0 )
b1000 *
b1000 +
b1000 ,
b1000 -
b1000 .
b1000 0
b11111 2
#345000
0!
0%
#350000
1!
1%
b100000 2
